{
  "_comment": "typelab トップページ用コンテンツデータ。新しい診断を追加するときはこのJSONを編集するだけでOK。",

  "popular": [
    {
      "rank": 1,
      "id": "16type",
      "title": "16タイプ 本格心理診断",
      "category": "MBTI系",
      "categoryColor": "var(--violet)",
      "heroGradient": "linear-gradient(135deg, #7b5ea7, #4a2d70)",
      "icon": "🧠",
      "takers": "42万人",
      "minutes": 5,
      "ctaColor": "var(--violet-light)",
      "ctaTextColor": "var(--violet)",
      "url": "diagnosis.html"
    },
    {
      "rank": 2,
      "id": "love-type",
      "title": "恋愛タイプ診断 〜 あなたの愛し方は？",
      "category": "恋愛",
      "categoryColor": "var(--rose)",
      "heroGradient": "linear-gradient(135deg, #c9607a, #8b3050)",
      "icon": "❤",
      "takers": "28万人",
      "minutes": 3,
      "ctaColor": "var(--rose-light)",
      "ctaTextColor": "var(--rose)",
      "url": "diagnosis.html"
    },
    {
      "rank": 3,
      "id": "deep-psych",
      "title": "深層心理テスト〜あなたの無意識が語るもの",
      "category": "深層心理",
      "categoryColor": "var(--teal)",
      "heroGradient": "linear-gradient(135deg, #3d8b8b, #1a5555)",
      "icon": "🔮",
      "takers": "19万人",
      "minutes": 4,
      "ctaColor": "var(--teal-light)",
      "ctaTextColor": "var(--teal)",
      "url": "diagnosis.html"
    }
  ],

  "categories": [
    {
      "id": "type",
      "icon": "🧠",
      "iconBg": "var(--violet-light)",
      "title": "タイプ診断",
      "description": "MBTI・16タイプ・ソシオニクスなど多様な類型論で自分を知る",
      "count": 32,
      "url": "#"
    },
    {
      "id": "love",
      "icon": "❤",
      "iconBg": "var(--rose-light)",
      "title": "恋愛・相性診断",
      "description": "恋愛スタイル・愛着スタイル・タイプ別相性を詳細分析",
      "count": 28,
      "url": "#"
    },
    {
      "id": "deep",
      "icon": "🔮",
      "iconBg": "var(--teal-light)",
      "title": "深層心理",
      "description": "ユング心理学・シャドウ・元型など無意識の世界を探る",
      "count": 20,
      "url": "#"
    },
    {
      "id": "fortune",
      "icon": "✨",
      "iconBg": "var(--amber-light)",
      "title": "占い・スピリチュアル",
      "description": "星座・数秘術・タロットを心理学的観点で解釈",
      "count": 24,
      "url": "#"
    },
    {
      "id": "work",
      "icon": "💼",
      "iconBg": "#e8f0fd",
      "title": "仕事・強み診断",
      "description": "職業適性・リーダーシップ・ストレス耐性を測定",
      "count": 18,
      "url": "#"
    },
    {
      "id": "growth",
      "icon": "🌱",
      "iconBg": "#f0fae8",
      "title": "成長・自己理解",
      "description": "防衛機制・成熟度・自己効力感を多面的に評価",
      "count": 16,
      "url": "#"
    },
    {
      "id": "cognitive",
      "icon": "🧩",
      "iconBg": "#fdf0e8",
      "title": "認知機能テスト",
      "description": "Ni・Ne・Si・Se・Ti・Te・Fi・Fe の8機能を精密測定",
      "count": 12,
      "url": "#"
    }
  ],

  "fortune": {
    "featured": {
      "title": "16タイプ別\n2025年の運命占い",
      "description": "MBTIタイプ × 占星術の融合。あなたのタイプが持つ今年の宿命と、最も輝く季節を解き明かします。16通りの専用リーディング付き。",
      "url": "https://utage-jpg.github.io/16type_fortune/",
      "ctaText": "✨ 占いを受ける"
    },
    "sub": [
      {
        "id": "astrology",
        "icon": "♈",
        "category": "占星術",
        "categoryColor": "var(--violet)",
        "title": "タイプ別 星座運命鑑定",
        "description": "あなたのMBTIと星座が交差する運命とは",
        "url": "#"
      },
      {
        "id": "numerology",
        "icon": "🔢",
        "category": "数秘術",
        "categoryColor": "var(--amber)",
        "title": "ライフパスナンバー診断",
        "description": "誕生日から導く魂の使命と人格の秘密",
        "url": "#"
      }
    ]
  },

  "premium": {
    "plans": [
      {
        "id": "free",
        "name": "FREE",
        "price": "¥0",
        "priceSub": "永久無料",
        "featured": false,
        "features": [
          "基本タイプ診断結果",
          "タイプ説明（基本版）",
          "SNS共有機能",
          "占いコンテンツ（一部）",
          "心理コラム閲覧"
        ],
        "ctaText": "無料で始める",
        "ctaUrl": "#"
      },
      {
        "id": "premium",
        "name": "PREMIUM",
        "price": "¥580",
        "priceSub": "/月（年払い ¥4,980）",
        "featured": true,
        "badge": "人気No.1",
        "features": [
          "詳細心理プロファイル（30P+）",
          "恋愛タイプ & 愛着スタイル分析",
          "全16タイプとの詳細相性データ",
          "認知機能スタック分析",
          "深層心理・シャドウ解析",
          "人格統合マップ（ビジュアル）",
          "月次タイプ別運勢",
          "診断履歴の保存"
        ],
        "ctaText": "初月無料で始める",
        "ctaUrl": "#"
      },
      {
        "id": "lab",
        "name": "LAB",
        "price": "¥1,480",
        "priceSub": "/月",
        "featured": false,
        "features": [
          "PREMIUMの全機能",
          "Socionics完全診断連携",
          "類型ポータル全コンテンツ",
          "研究データベース閲覧",
          "有名人タイプ比較分析",
          "コミュニティアクセス",
          "診断レポートPDFダウンロード"
        ],
        "ctaText": "LABを始める",
        "ctaUrl": "#"
      }
    ]
  },

  "columns": [
    {
      "id": "intj-love",
      "tag": "INTJ",
      "tagColor": "var(--violet)",
      "title": "INTJが恋愛で陥りやすい罠と、理想の関係を築く方法",
      "date": "2025年3月",
      "readMin": 8,
      "url": "#"
    },
    {
      "id": "shadow-self",
      "tag": "深層心理",
      "tagColor": "var(--teal)",
      "title": "シャドウとは何か — ユング心理学から見る「もう一人の自分」",
      "date": "2025年3月",
      "readMin": 12,
      "url": "#"
    },
    {
      "id": "attachment-style",
      "tag": "愛着理論",
      "tagColor": "var(--rose)",
      "title": "愛着スタイル4タイプ解説 — あなたの恋愛パターンの根源",
      "date": "2025年2月",
      "readMin": 10,
      "url": "#"
    }
  ],

  "deepdive": [
    {
      "id": "ruikei",
      "title": "類型ポータル",
      "subtitle": "中級者向け",
      "description": "ソシオニクス・エニアグラム・MBTI を体系的に学ぶ。16タイプの深い理解へ。",
      "icon": "📚",
      "color": "var(--violet)",
      "url": "https://utage-jpg.github.io/ruikei_portal/",
      "external": true
    },
    {
      "id": "socio",
      "title": "Socionics Lab",
      "subtitle": "研究・上級者向け",
      "description": "ロシア発の精密類型論「ソシオニクス」を日本語で。学術的なタイプ判定。",
      "icon": "🔬",
      "color": "var(--teal)",
      "url": "https://utage-jpg.github.io/socio_lens/",
      "external": true
    },
    {
      "id": "fortune16",
      "title": "16タイプ占い",
      "subtitle": "今日の運勢",
      "description": "16タイプ別の今日の運勢・今週の星読み。毎日更新。",
      "icon": "🔮",
      "color": "var(--gold)",
      "url": "https://utage-jpg.github.io/16type_fortune/",
      "external": true
    }
  ]
}
